airlabs/__init__.py
airlabs/endpoints.py
airlabs/functions.py
airlabs-0.0.7.dist-info/LICENSE
airlabs-0.0.7.dist-info/METADATA
airlabs-0.0.7.dist-info/WHEEL
airlabs-0.0.7.dist-info/top_level.txt
airlabs-0.0.7.dist-info/RECORD
