Metadata-Version: 2.1
Name: airlabs
Version: 0.0.7
Summary: Python wrapper for AirLabs
Home-page: https://github.com/calebyhan/AirLabs
Author: Caleb Han
Author-email: calebhantech@gmail.com
License: MIT
Classifier: License :: OSI Approved :: MIT License
Classifier: Programming Language :: Python :: 3
Classifier: Operating System :: OS Independent
License-File: LICENSE
